ovos_core/__init__.py
ovos_core/__main__.py
ovos_core/skill_installer.py
ovos_core/skill_manager.py
ovos_core/transformers.py
ovos_core/version.py
ovos_core/intent_services/__init__.py
ovos_core/intent_services/converse_service.py
ovos_core/intent_services/fallback_service.py
ovos_core/intent_services/service.py
ovos_core/intent_services/stop_service.py
ovos_core/intent_services/locale/ca-es/global_stop.intent
ovos_core/intent_services/locale/ca-es/stop.intent
ovos_core/intent_services/locale/da-dk/global_stop.intent
ovos_core/intent_services/locale/da-dk/stop.intent
ovos_core/intent_services/locale/de-de/global_stop.intent
ovos_core/intent_services/locale/de-de/stop.intent
ovos_core/intent_services/locale/en-us/global_stop.intent
ovos_core/intent_services/locale/en-us/stop.intent
ovos_core/intent_services/locale/es-es/global_stop.intent
ovos_core/intent_services/locale/es-es/stop.intent
ovos_core/intent_services/locale/eu/global_stop.intent
ovos_core/intent_services/locale/eu/stop.intent
ovos_core/intent_services/locale/fa-ir/global_stop.intent
ovos_core/intent_services/locale/fa-ir/stop.intent
ovos_core/intent_services/locale/fr-fr/global_stop.intent
ovos_core/intent_services/locale/fr-fr/stop.intent
ovos_core/intent_services/locale/gl-es/global_stop.intent
ovos_core/intent_services/locale/gl-es/stop.intent
ovos_core/intent_services/locale/it-it/global_stop.intent
ovos_core/intent_services/locale/it-it/stop.intent
ovos_core/intent_services/locale/nl-be/stop.intent
ovos_core/intent_services/locale/nl-nl/global_stop.intent
ovos_core/intent_services/locale/nl-nl/stop.intent
ovos_core/intent_services/locale/pl-pl/global_stop.intent
ovos_core/intent_services/locale/pl-pl/stop.intent
ovos_core/intent_services/locale/pt-br/global_stop.intent
ovos_core/intent_services/locale/pt-br/stop.intent
ovos_core/intent_services/locale/pt-pt/global_stop.intent
ovos_core/intent_services/locale/pt-pt/stop.intent
ovos_core/intent_services/locale/uk-ua/global_stop.intent
ovos_core-2.1.1.dist-info/licenses/LICENSE
ovos_core-2.1.1.dist-info/METADATA
ovos_core-2.1.1.dist-info/WHEEL
ovos_core-2.1.1.dist-info/entry_points.txt
ovos_core-2.1.1.dist-info/top_level.txt
ovos_core-2.1.1.dist-info/RECORD
