Metadata-Version: 2.4
Name: ovos_core
Version: 2.1.1
Summary: The spiritual successor to Mycroft AI, OVOS is flexible voice assistant software that can be run almost anywhere!
Home-page: https://github.com/OpenVoiceOS/ovos-core
License: Apache-2.0
Classifier: Development Status :: 4 - Beta
Classifier: Programming Language :: Python :: 3
Classifier: License :: OSI Approved :: Apache Software License
License-File: LICENSE
Requires-Dist: requests<3.0,>=2.26
Requires-Dist: python-dateutil<3.0,>=2.6
Requires-Dist: watchdog<3.0,>=2.1
Requires-Dist: combo-lock<0.4,>=0.2.2
Requires-Dist: ovos-utils<1.0.0,>=0.8.2a1
Requires-Dist: ovos_bus_client<2.0.0,>=1.3.6a1
Requires-Dist: ovos-plugin-manager<3.0.0,>=1.0.3
Requires-Dist: ovos-config<3.0.0,>=0.0.13
Requires-Dist: ovos-workshop<8.0.0,>=7.0.6
Requires-Dist: rapidfuzz<4.0,>=3.6
Requires-Dist: langcodes
Provides-Extra: test
Requires-Dist: coveralls>=1.8.2; extra == "test"
Requires-Dist: flake8>=3.7.9; extra == "test"
Requires-Dist: pytest>=5.2.4; extra == "test"
Requires-Dist: pytest-cov>=2.8.1; extra == "test"
Requires-Dist: pytest-testmon>=2.1.3; extra == "test"
Requires-Dist: pytest-randomly>=3.16.0; extra == "test"
Requires-Dist: cov-core>=1.15.0; extra == "test"
Requires-Dist: ovoscope<1.0.0,>=0.7.2; extra == "test"
Provides-Extra: mycroft
Requires-Dist: ovos_PHAL[extras]<1.0.0,>=0.2.9; extra == "mycroft"
Requires-Dist: ovos-audio[extras]<2.0.0,>=1.0.1; extra == "mycroft"
Requires-Dist: ovos-audio<2.0.0,>=1.0.1; extra == "mycroft"
Requires-Dist: ovos-gui[extras]<2.0.0,>=1.3.3; extra == "mycroft"
Requires-Dist: ovos-messagebus<1.0.0,>=0.0.7; extra == "mycroft"
Requires-Dist: ovos-dinkum-listener[extras]<1.0.0,>=0.4.1; extra == "mycroft"
Provides-Extra: lgpl
Requires-Dist: ovos_padatious<2.0.0,>=1.4.2; extra == "lgpl"
Requires-Dist: fann2<1.1.0,>=1.0.7; extra == "lgpl"
Provides-Extra: plugins
Requires-Dist: ovos-utterance-corrections-plugin<1.0.0,>=0.1.1; extra == "plugins"
Requires-Dist: ovos-utterance-plugin-cancel<1.0.0,>=0.2.3; extra == "plugins"
Requires-Dist: ovos-bidirectional-translation-plugin<1.0.0,>=0.1.0; extra == "plugins"
Requires-Dist: ovos-translate-server-plugin<1.0.0,>=0.0.4; extra == "plugins"
Requires-Dist: ovos-utterance-normalizer<1.0.0,>=0.2.2; extra == "plugins"
Requires-Dist: ovos-number-parser<1.0.0,>=0.0.1; extra == "plugins"
Requires-Dist: ovos-date-parser<1.0.0,>=0.0.3; extra == "plugins"
Requires-Dist: ovos-m2v-pipeline<1.0.0,>=0.0.6; extra == "plugins"
Requires-Dist: ovos-common-query-pipeline-plugin<2.0.0,>=1.1.8; extra == "plugins"
Requires-Dist: ovos-adapt-parser<2.0.0,>=1.0.6; extra == "plugins"
Requires-Dist: ovos_ocp_pipeline_plugin<2.0.0,>=1.1.18a1; extra == "plugins"
Requires-Dist: ovos-persona<1.0.0,>=0.6.23; extra == "plugins"
Requires-Dist: padacioso<2.0.0,>=1.0.0; extra == "plugins"
Requires-Dist: keyword-template-matcher<1.0.0,>=0.1.1; extra == "plugins"
Requires-Dist: ahocorasick-ner<1.0.0,>=0.1.1; extra == "plugins"
Provides-Extra: skills-essential
Requires-Dist: ovos-skill-fallback-unknown<1.0.0,>=0.1.9; extra == "skills-essential"
Requires-Dist: ovos-skill-alerts<1.0.0,>=0.1.10; extra == "skills-essential"
Requires-Dist: ovos-skill-personal<1.0.0,>=0.1.19; extra == "skills-essential"
Requires-Dist: ovos-skill-date-time<2.0.0,>=1.1.3; extra == "skills-essential"
Requires-Dist: ovos-skill-hello-world<1.0.0,>=0.1.10; extra == "skills-essential"
Requires-Dist: ovos-skill-spelling<1.0.0,>=0.2.5; extra == "skills-essential"
Requires-Dist: ovos-skill-diagnostics<1.0.0,>=0.0.2; extra == "skills-essential"
Requires-Dist: ovos-skill-parrot<1.0.0,>=0.1.25; extra == "skills-essential"
Requires-Dist: ovos-skill-count<1.0.0,>=0.0.1; extra == "skills-essential"
Requires-Dist: ovos-skill-randomness<1.0.0,>=0.1.2; python_version >= "3.10" and extra == "skills-essential"
Provides-Extra: skills-extra
Requires-Dist: ovos-skill-wordnet<1.0.0,>=0.2.5; extra == "skills-extra"
Requires-Dist: ovos-skill-laugh<1.0.0,>=0.1.1; extra == "skills-extra"
Requires-Dist: ovos-skill-number-facts<1.0.0,>=0.1.12; extra == "skills-extra"
Requires-Dist: ovos-skill-iss-location<1.0.0,>=0.2.16; extra == "skills-extra"
Requires-Dist: ovos-skill-cmd<1.0.0,>=0.2.11; extra == "skills-extra"
Requires-Dist: ovos-skill-moviemaster<1.0.0,>=0.0.12; extra == "skills-extra"
Requires-Dist: ovos-skill-confucius-quotes<1.0.0,>=0.1.13; extra == "skills-extra"
Requires-Dist: ovos-skill-icanhazdadjokes<1.0.0,>=0.3.7; extra == "skills-extra"
Requires-Dist: ovos-skill-camera; extra == "skills-extra"
Provides-Extra: skills-audio
Requires-Dist: ovos-skill-boot-finished<1.0.0,>=0.4.8; extra == "skills-audio"
Requires-Dist: ovos-skill-audio-recording<1.0.0,>=0.2.4; extra == "skills-audio"
Requires-Dist: ovos-skill-dictation<1.0.0,>=0.2.5; extra == "skills-audio"
Requires-Dist: ovos-skill-volume<1.0.0,>=0.1.16; extra == "skills-audio"
Requires-Dist: ovos-skill-naptime<1.0.0,>=0.3.15; extra == "skills-audio"
Provides-Extra: skills-desktop
Requires-Dist: ovos-skill-application-launcher<1.0.0,>=0.5.14; extra == "skills-desktop"
Requires-Dist: ovos-skill-wallpapers<3.0.0,>=1.0.2; extra == "skills-desktop"
Requires-Dist: ovos-skill-screenshot<1.0.0,>=0.0.2; extra == "skills-desktop"
Provides-Extra: skills-internet
Requires-Dist: ovos-skill-weather<2.0.0,>=1.0.3; extra == "skills-internet"
Requires-Dist: ovos-skill-ddg<1.0.0,>=0.3.5; extra == "skills-internet"
Requires-Dist: ovos-skill-wolfie<1.0.0,>=0.5.8; extra == "skills-internet"
Requires-Dist: ovos-skill-wikipedia<1.0.0,>=0.8.13; extra == "skills-internet"
Requires-Dist: ovos-skill-wikihow<1.0.0,>=0.3.3; extra == "skills-internet"
Requires-Dist: ovos-skill-speedtest<1.0.0,>=0.3.6; extra == "skills-internet"
Requires-Dist: ovos-skill-ip<1.0.0,>=0.2.5; extra == "skills-internet"
Provides-Extra: skills-gui
Requires-Dist: ovos-skill-homescreen<4.0.0,>=3.0.3; extra == "skills-gui"
Requires-Dist: ovos-skill-screenshot<1.0.0,>=0.0.2; extra == "skills-gui"
Requires-Dist: ovos-skill-color-picker<1.0.0,>=0.0.2; extra == "skills-gui"
Provides-Extra: skills-media
Requires-Dist: ovos-skill-somafm<1.0.0,>=0.1.3; extra == "skills-media"
Requires-Dist: ovos-skill-news<1.0.0,>=0.4.6a1; extra == "skills-media"
Requires-Dist: ovos-skill-pyradios<1.0.0,>=0.1.5; extra == "skills-media"
Requires-Dist: ovos-skill-local-media<1.0.0,>=0.2.12; extra == "skills-media"
Requires-Dist: ovos-skill-youtube-music<1.0.0,>=0.1.7; extra == "skills-media"
Provides-Extra: skills-ca
Requires-Dist: ovos-skill-fuster-quotes; extra == "skills-ca"
Requires-Dist: ovos-skill-word-of-the-day; extra == "skills-ca"
Provides-Extra: skills-pt
Requires-Dist: ovos-skill-word-of-the-day; extra == "skills-pt"
Provides-Extra: skills-gl
Requires-Dist: ovos-skill-word-of-the-day>=0.2.0; extra == "skills-gl"
Provides-Extra: skills-en
Requires-Dist: ovos-skill-word-of-the-day; extra == "skills-en"
Requires-Dist: ovos-skill-days-in-history<1.0.0,>=0.3.11; extra == "skills-en"
Dynamic: classifier
Dynamic: description
Dynamic: description-content-type
Dynamic: home-page
Dynamic: license
Dynamic: license-file
Dynamic: provides-extra
Dynamic: requires-dist
Dynamic: summary
